{
	"caption": {
		"Cn_Simp": "",
		"en_US": "Advanced Classes Mod 1.093",
		"ru_RU": ""
	},
	"description": {
		"full": {
			"Cn_Simp": "",
			"en_US": "Readme.txt",
			"ru_RU": ""
		},
		"short": {
			"Cn_Simp": "",
			"en_US": "Advanced Classes Mod  \r\nA Mod by Perry R, AlfWithCake and anti-victor for Heroes 3 ERA \r\n\r\nAdvanced Classes Mod provides a new class and skill system for Heroes 3. Now it is possible to play three very distinct classes, each with their own strengths and weaknesses.\r\n",
			"ru_RU": ""
		}
	},
	"author": "PerryR",
	"homepage": "http://heroescommunity.com/viewthread.php3?TID=41718",
	"icon": {
		"file": "Iv.ico",
		"index": 0
	},
	"mod_version": "1.093",
	"priority": 2,
	"compatibility": {
		"class": "default",
		"entries": {}
	},
	"platform": "era",
	"info_version": "1.0",
	"plugins": {},
	"category": "gameplay"
}